geocondense/__init__.py
geocondense/_core.cp39-win_amd64.pyd
geocondense/_core.pyi
geocondense/condense.py
geocondense/condense_geojson.py
geocondense/condense_pointcloud.py
geocondense/dissect_geojson.py
geocondense/py.typed
geocondense/utils.py
geocondense-0.0.4.dist-info/METADATA
geocondense-0.0.4.dist-info/WHEEL
geocondense-0.0.4.dist-info/licenses/LICENSE
geocondense-0.0.4.dist-info/RECORD
