Metadata-Version: 2.1
Name: geocondense
Version: 0.0.4
Summary: geocondense
Author-Email: district10 <dvorak4tzx@gmail.com>
Classifier: Development Status :: 4 - Beta
Classifier: License :: OSI Approved :: MIT License
Classifier: Programming Language :: Python :: 3 :: Only
Classifier: Programming Language :: Python :: 3.7
Classifier: Programming Language :: Python :: 3.8
Classifier: Programming Language :: Python :: 3.9
Classifier: Programming Language :: Python :: 3.10
Classifier: Programming Language :: Python :: 3.11
Classifier: Programming Language :: Python :: 3.12
Requires-Python: >=3.7
Requires-Dist: concave_hull
Requires-Dist: fire
Requires-Dist: loguru
Requires-Dist: numpy
Requires-Dist: open3d
Requires-Dist: polyline_ruler
Requires-Dist: pytest; extra == "test"
Provides-Extra: test
